MANIFEST.in
README.rst
setup.py
docs/CONTRIBUTORS.rst
docs/HISTORY.rst
docs/LICENSE.rst
docs/api.rst
docs/auth.rst
docs/conf.py
docs/crud.rst
docs/customizing.rst
docs/dexterity.rst
docs/examples.rst
docs/index.rst
docs/installation.rst
docs/links.rst
docs/quickstart.rst
src/plone/__init__.py
src/plone.jsonapi.routes.egg-info/PKG-INFO
src/plone.jsonapi.routes.egg-info/SOURCES.txt
src/plone.jsonapi.routes.egg-info/dependency_links.txt
src/plone.jsonapi.routes.egg-info/entry_points.txt
src/plone.jsonapi.routes.egg-info/namespace_packages.txt
src/plone.jsonapi.routes.egg-info/not-zip-safe
src/plone.jsonapi.routes.egg-info/requires.txt
src/plone.jsonapi.routes.egg-info/top_level.txt
src/plone/jsonapi/__init__.py
src/plone/jsonapi/routes/__init__.py
src/plone/jsonapi/routes/api.py
src/plone/jsonapi/routes/batch.py
src/plone/jsonapi/routes/catalog.py
src/plone/jsonapi/routes/configure.zcml
src/plone/jsonapi/routes/datamanagers.py
src/plone/jsonapi/routes/dataproviders.py
src/plone/jsonapi/routes/exceptions.py
src/plone/jsonapi/routes/fieldmanagers.py
src/plone/jsonapi/routes/interfaces.py
src/plone/jsonapi/routes/meta.zcml
src/plone/jsonapi/routes/request.py
src/plone/jsonapi/routes/underscore.py
src/plone/jsonapi/routes/version.py
src/plone/jsonapi/routes/zcml.py
src/plone/jsonapi/routes/docs/Readme.txt
src/plone/jsonapi/routes/providers/__init__.py
src/plone/jsonapi/routes/providers/auth.py
src/plone/jsonapi/routes/providers/content.py
src/plone/jsonapi/routes/providers/users.py
src/plone/jsonapi/routes/providers/version.py
src/plone/jsonapi/routes/tests/TestDoc.docx
src/plone/jsonapi/routes/tests/__init__.py
src/plone/jsonapi/routes/tests/base.py
src/plone/jsonapi/routes/tests/robot_tests.txt
src/plone/jsonapi/routes/tests/test_adapters.py
src/plone/jsonapi/routes/tests/test_api.py
src/plone/jsonapi/routes/tests/test_doctests.py
src/plone/jsonapi/routes/tests/test_files_api.py
src/plone/jsonapi/routes/tests/test_request.py
src/plone/jsonapi/routes/tests/test_robot.py
src/plone/jsonapi/routes/tests/test_setup.py
src/plone/jsonapi/routes/tests/test_underscore.py