Metadata-Version: 1.1
Name: plone.jsonapi.routes
Version: 0.9.4
Summary: Plone JSON API -- Routes
Home-page: https://github.com/collective/plone.jsonapi.routes
Author: Ramon Bartl
Author-email: rb@ridingbytes.com
License: MIT
Platform: UNKNOWN
Classifier: Programming Language :: Python
Classifier: Framework :: Plone
Classifier: Framework :: Plone :: 4.3
Classifier: Framework :: Plone :: 5.0
Classifier: Framework :: Plone :: 5.1
Classifier: Framework :: Zope2
